{"version":"2.1","canteen_id":"stucafe-connollystr","weeks":[{"number":14,"year":2026,"days":[{"date":"2026-03-31","dishes":[{"name":"Pinsa","prices":{"students":{"base_price":0,"price_per_unit":0.9,"unit":"100g"},"staff":{"base_price":0,"price_per_unit":1.15,"unit":"100g"},"guests":{"base_price":0,"price_per_unit":1.6,"unit":"100g"}},"labels":["CEREAL","GLUTEN","LACTOSE","MILK","SOY","VEGETARIAN","WHEAT"],"dish_type":"Vegetarisch/fleischlos"},{"name":"Pinsa with rocket","prices":{"students":{"base_price":0,"price_per_unit":0.9,"unit":"100g"},"staff":{"base_price":0,"price_per_unit":1.15,"unit":"100g"},"guests":{"base_price":0,"price_per_unit":1.6,"unit":"100g"}},"labels":["CEREAL","GLUTEN","SOY","VEGAN","VEGETARIAN","WHEAT"],"dish_type":"Vegetarisch/fleischlos"},{"name":"Pinsa with ham, salami or minced meat","prices":{"students":{"base_price":1.0,"price_per_unit":0.9,"unit":"100g"},"staff":{"base_price":1.0,"price_per_unit":1.15,"unit":"100g"},"guests":{"base_price":1.0,"price_per_unit":1.6,"unit":"100g"}},"labels":["ANTIOXIDANTS","BEEF","CEREAL","DYESTUFF","GARLIC","GLUTEN","LACTOSE","MEAT","MILK","MUSTARD","PHOSPHATES","PORK","PRESERVATIVES","SOY","WHEAT"],"dish_type":"Fleisch"},{"name":"Grilled chicken skewer with spicy tomato salsa","prices":{"students":{"base_price":1.0,"price_per_unit":0.9,"unit":"100g"},"staff":{"base_price":1.0,"price_per_unit":1.15,"unit":"100g"},"guests":{"base_price":1.0,"price_per_unit":1.6,"unit":"100g"}},"labels":["MEAT"],"dish_type":"Fleisch"},{"name":"Mini spring rolls with vegetable curry rice","prices":{"students":{"base_price":0,"price_per_unit":0.9,"unit":"100g"},"staff":{"base_price":0,"price_per_unit":1.15,"unit":"100g"},"guests":{"base_price":0,"price_per_unit":1.6,"unit":"100g"}},"labels":["CELERY","CEREAL","DYESTUFF","FISH","GARLIC","GLUTEN","MUSTARD","PEANUTS","SESAME","SHELL_FRUITS","SOY","VEGAN","VEGETARIAN","WHEAT"],"dish_type":"Vegan"},{"name":"Chocolate cream","prices":{"students":{"base_price":0,"price_per_unit":0.9,"unit":"100g"},"staff":{"base_price":0,"price_per_unit":1.15,"unit":"100g"},"guests":{"base_price":0,"price_per_unit":1.6,"unit":"100g"}},"labels":["ALMONDS","BARLEY","CASHEWS","CEREAL","GLUTEN","HAZELNUTS","LACTOSE","MILK","OAT","PEANUTS","SESAME","SHELLFISH","SHELL_FRUITS","SOY","VEGETARIAN","WALNUTS","WHEAT"],"dish_type":"Dessert (Glas)"}]},{"date":"2026-04-01","dishes":[{"name":"Dumplings with lime and basil filling with tomato cream sauce","prices":{"students":{"base_price":0,"price_per_unit":0.9,"unit":"100g"},"staff":{"base_price":0,"price_per_unit":1.15,"unit":"100g"},"guests":{"base_price":0,"price_per_unit":1.6,"unit":"100g"}},"labels":["CEREAL","CHICKEN_EGGS","GLUTEN","LACTOSE","MILK","VEGETARIAN","WHEAT"],"dish_type":"Pasta"},{"name":"Three spinach dumplings with tomato sauce","prices":{"students":{"base_price":0,"price_per_unit":0.9,"unit":"100g"},"staff":{"base_price":0,"price_per_unit":1.15,"unit":"100g"},"guests":{"base_price":0,"price_per_unit":1.6,"unit":"100g"}},"labels":["CEREAL","CHICKEN_EGGS","GLUTEN","LACTOSE","MILK","VEGETARIAN","WHEAT"],"dish_type":"Pasta"},{"name":"Cevapcici (5 pieces) with ajvar","prices":{"students":{"base_price":1.0,"price_per_unit":0.9,"unit":"100g"},"staff":{"base_price":1.0,"price_per_unit":1.15,"unit":"100g"},"guests":{"base_price":1.0,"price_per_unit":1.6,"unit":"100g"}},"labels":["BEEF","CELERY","CEREAL","CHICKEN_EGGS","GARLIC","GLUTEN","MEAT","MUSTARD","SOY","WHEAT"],"dish_type":"Fleisch"},{"name":"Dessert of the day","prices":{"students":{"base_price":1.0,"price_per_unit":0.9,"unit":"100g"},"staff":{"base_price":1.0,"price_per_unit":1.15,"unit":"100g"},"guests":{"base_price":1.0,"price_per_unit":1.6,"unit":"100g"}},"labels":["MEAT"],"dish_type":"Dessert (Glas)"}]},{"date":"2026-04-02","dishes":[]},{"date":"2026-04-03","dishes":[]}]},{"number":15,"year":2026,"days":[{"date":"2026-04-06","dishes":[]},{"date":"2026-04-07","dishes":[]},{"date":"2026-04-08","dishes":[{"name":"Gnocchi with fresh pan-fried vegetables","prices":{"students":{"base_price":0,"price_per_unit":0.9,"unit":"100g"},"staff":{"base_price":0,"price_per_unit":1.15,"unit":"100g"},"guests":{"base_price":0,"price_per_unit":1.6,"unit":"100g"}},"labels":["CEREAL","GLUTEN","PRESERVATIVES","VEGAN","VEGETARIAN","WHEAT"],"dish_type":"Pasta"},{"name":"Orange bomb detox (stew with sweet potato, carrot, potato and coconut)","prices":{"students":{"base_price":0,"price_per_unit":0.9,"unit":"100g"},"staff":{"base_price":0,"price_per_unit":1.15,"unit":"100g"},"guests":{"base_price":0,"price_per_unit":1.6,"unit":"100g"}},"labels":["ANTIOXIDANTS","PRESERVATIVES","VEGAN","VEGETARIAN"],"dish_type":"Vegetarisch/fleischlos"},{"name":"Chicken fricassee with peas and mushrooms","prices":{"students":{"base_price":1.0,"price_per_unit":0.9,"unit":"100g"},"staff":{"base_price":1.0,"price_per_unit":1.15,"unit":"100g"},"guests":{"base_price":1.0,"price_per_unit":1.6,"unit":"100g"}},"labels":["ALCOHOL","CEREAL","GLUTEN","LACTOSE","MEAT","MILK","SULFITES","SULPHURS","WHEAT"],"dish_type":"Fleisch"},{"name":"Dessert of the day","prices":{"students":{"base_price":1.0,"price_per_unit":0.9,"unit":"100g"},"staff":{"base_price":1.0,"price_per_unit":1.15,"unit":"100g"},"guests":{"base_price":1.0,"price_per_unit":1.6,"unit":"100g"}},"labels":["MEAT"],"dish_type":"Dessert (Glas)"}]},{"date":"2026-04-09","dishes":[{"name":"Dumplings with lemon-and-basil filling and paprika sauce","prices":{"students":{"base_price":0,"price_per_unit":0.9,"unit":"100g"},"staff":{"base_price":0,"price_per_unit":1.15,"unit":"100g"},"guests":{"base_price":0,"price_per_unit":1.6,"unit":"100g"}},"labels":["CEREAL","CHICKEN_EGGS","GLUTEN","LACTOSE","MILK","PRESERVATIVES","VEGETARIAN","WHEAT"],"dish_type":"Pasta"},{"name":"Fried chicken wings with barbecue sauce","prices":{"students":{"base_price":1.0,"price_per_unit":0.9,"unit":"100g"},"staff":{"base_price":1.0,"price_per_unit":1.15,"unit":"100g"},"guests":{"base_price":1.0,"price_per_unit":1.6,"unit":"100g"}},"labels":["CELERY","GARLIC","MEAT","MUSTARD","PRESERVATIVES","SWEETENERS"],"dish_type":"Fleisch"},{"name":"Cauliflower and cheese medallion with salsa","prices":{"students":{"base_price":0,"price_per_unit":0.9,"unit":"100g"},"staff":{"base_price":0,"price_per_unit":1.15,"unit":"100g"},"guests":{"base_price":0,"price_per_unit":1.6,"unit":"100g"}},"labels":["CELERY","CEREAL","GLUTEN","LACTOSE","MILK","PRESERVATIVES","SWEETENERS","VEGETARIAN","WHEAT"],"dish_type":"Vegan"},{"name":"Dessert of the day","prices":{"students":{"base_price":1.0,"price_per_unit":0.9,"unit":"100g"},"staff":{"base_price":1.0,"price_per_unit":1.15,"unit":"100g"},"guests":{"base_price":1.0,"price_per_unit":1.6,"unit":"100g"}},"labels":["MEAT"],"dish_type":"Dessert (Glas)"}]},{"date":"2026-04-10","dishes":[{"name":"Fish (pollack, 7 pieces) and chips with tartar sauce","prices":{"students":{"base_price":1.5,"price_per_unit":0.9,"unit":"100g"},"staff":{"base_price":1.5,"price_per_unit":1.15,"unit":"100g"},"guests":{"base_price":1.5,"price_per_unit":1.6,"unit":"100g"}},"labels":["CEREAL","CHICKEN_EGGS","DYESTUFF","FISH","GLUTEN","LACTOSE","MILK","MUSTARD","SWEETENERS","WHEAT"],"dish_type":"Fisch"},{"name":"Curd cheese strudel with pears and vanilla sauce (without raisins)","prices":{"students":{"base_price":0,"price_per_unit":0.9,"unit":"100g"},"staff":{"base_price":0,"price_per_unit":1.15,"unit":"100g"},"guests":{"base_price":0,"price_per_unit":1.6,"unit":"100g"}},"labels":["CEREAL","CHICKEN_EGGS","GLUTEN","LACTOSE","MILK","PRESERVATIVES","VEGETARIAN","WHEAT"],"dish_type":"Süßspeise"},{"name":"Colorful vegetable curry with lentils and coconut bulgur","prices":{"students":{"base_price":0,"price_per_unit":0.9,"unit":"100g"},"staff":{"base_price":0,"price_per_unit":1.15,"unit":"100g"},"guests":{"base_price":0,"price_per_unit":1.6,"unit":"100g"}},"labels":["ANTIOXIDANTS","CEREAL","GARLIC","GLUTEN","PRESERVATIVES","SOY","VEGAN","VEGETARIAN","WHEAT"],"dish_type":"Vegan"}]}]},{"number":16,"year":2026,"days":[{"date":"2026-04-13","dishes":[{"name":"Pasta Verdura","prices":{"students":{"base_price":0,"price_per_unit":0.9,"unit":"100g"},"staff":{"base_price":0,"price_per_unit":1.15,"unit":"100g"},"guests":{"base_price":0,"price_per_unit":1.6,"unit":"100g"}},"labels":["CEREAL","GLUTEN","VEGAN","VEGETARIAN","WHEAT"],"dish_type":"Pasta"},{"name":"Yufka dough bun with spinach filling","prices":{"students":{"base_price":0,"price_per_unit":0.9,"unit":"100g"},"staff":{"base_price":0,"price_per_unit":1.15,"unit":"100g"},"guests":{"base_price":0,"price_per_unit":1.6,"unit":"100g"}},"labels":["ANTIOXIDANTS","CELERY","CEREAL","FLAVOR_ENHANCER","GLUTEN","PRESERVATIVES","SOY","SULFITES","SULPHURS","VEGAN","VEGETARIAN","WHEAT"],"dish_type":"Vegetarisch/fleischlos"},{"name":"Chive dip","prices":{"students":{"base_price":0,"price_per_unit":0.9,"unit":"100g"},"staff":{"base_price":0,"price_per_unit":1.15,"unit":"100g"},"guests":{"base_price":0,"price_per_unit":1.6,"unit":"100g"}},"labels":["LACTOSE","MILK","VEGETARIAN"],"dish_type":"Vegetarisch/fleischlos"},{"name":"Wiener-style pork schnitzel (1 piece)","prices":{"students":{"base_price":1.0,"price_per_unit":0.9,"unit":"100g"},"staff":{"base_price":1.0,"price_per_unit":1.15,"unit":"100g"},"guests":{"base_price":1.0,"price_per_unit":1.6,"unit":"100g"}},"labels":["CEREAL","GARLIC","GLUTEN","MEAT","PORK","PRESERVATIVES","WHEAT"],"dish_type":"Fleisch"},{"name":"Kaiserschmarrn","prices":{"students":{"base_price":0,"price_per_unit":0.9,"unit":"100g"},"staff":{"base_price":0,"price_per_unit":1.15,"unit":"100g"},"guests":{"base_price":0,"price_per_unit":1.6,"unit":"100g"}},"labels":["ANTIOXIDANTS","CEREAL","CHICKEN_EGGS","GLUTEN","LACTOSE","MILK","VEGETARIAN","WHEAT"],"dish_type":"Dessert (Glas)"}]}]}]}