{"number":31,"year":2022,"days":[{"date":"2022-08-01","dishes":[{"name":"Currywurst mit Honig-Ingwer-Ketchup","prices":{"students":{"base_price":0.5,"price_per_unit":0.8,"unit":"100g"},"staff":{"base_price":0.5,"price_per_unit":1.0,"unit":"100g"},"guests":{"base_price":0.5,"price_per_unit":1.35,"unit":"100g"}},"labels":["BEEF","MEAT","MUSTARD","PHOSPATES","PORK","SWEETENERS"],"dish_type":"Aktionsessen 2"},{"name":"Ravioli mit Pilzfüllung in pikanter Kräutersauce","prices":{"students":{"base_price":0,"price_per_unit":0.8,"unit":"100g"},"staff":{"base_price":0,"price_per_unit":1.0,"unit":"100g"},"guests":{"base_price":0,"price_per_unit":1.35,"unit":"100g"}},"labels":["CEREAL","CHICKEN_EGGS","GARLIC","GLUTEN","LACTOSE","MILK","VEGETARIAN","WHEAT"],"dish_type":"Aktionsessen 3"}]},{"date":"2022-08-02","dishes":[{"name":"Senner Rösti mit Paprika-Gurken-Dip","prices":{"students":{"base_price":0,"price_per_unit":0.8,"unit":"100g"},"staff":{"base_price":0,"price_per_unit":1.0,"unit":"100g"},"guests":{"base_price":0,"price_per_unit":1.35,"unit":"100g"}},"labels":["ANTIOXIDANTS","SOY","VEGAN","VEGETARIAN"],"dish_type":"Aktionsessen 3"},{"name":"Grünes Hähnchen-Curry mit Wokgemüse","prices":{"students":{"base_price":1.0,"price_per_unit":0.8,"unit":"100g"},"staff":{"base_price":1.0,"price_per_unit":1.0,"unit":"100g"},"guests":{"base_price":1.0,"price_per_unit":1.35,"unit":"100g"}},"labels":["CEREAL","GARLIC","GLUTEN","MEAT","PEANUTS","PRESERVATIVES","SOY","WHEAT"],"dish_type":"Aktionsessen 7"}]},{"date":"2022-08-03","dishes":[{"name":"Grünkohl-Hanf-Bällchen mit veganem Soja-Joghurt-Dip","prices":{"students":{"base_price":0,"price_per_unit":0.8,"unit":"100g"},"staff":{"base_price":0,"price_per_unit":1.0,"unit":"100g"},"guests":{"base_price":0,"price_per_unit":1.35,"unit":"100g"}},"labels":["ANTIOXIDANTS","SOY","VEGAN","VEGETARIAN"],"dish_type":"Aktionsessen 5"},{"name":"Überbackenes Hacksteak griechische Art mit Tsatsiki","prices":{"students":{"base_price":1.0,"price_per_unit":0.8,"unit":"100g"},"staff":{"base_price":1.0,"price_per_unit":1.0,"unit":"100g"},"guests":{"base_price":1.0,"price_per_unit":1.35,"unit":"100g"}},"labels":["ANTIOXIDANTS","BEEF","DYESTUFF","GARLIC","LACTOSE","MEAT","MILK","MUSTARD","SULFITES","SULPHURS"],"dish_type":"Aktionsessen 8"}]},{"date":"2022-08-04","dishes":[{"name":"Pasta mit Rucola, Frühlingszwiebeln und Kirschtomaten , dazu Hartkäse","prices":{"students":{"base_price":0,"price_per_unit":0.8,"unit":"100g"},"staff":{"base_price":0,"price_per_unit":1.0,"unit":"100g"},"guests":{"base_price":0,"price_per_unit":1.35,"unit":"100g"}},"labels":["CEREAL","CHICKEN_EGGS","GLUTEN","LACTOSE","MILK","PRESERVATIVES","VEGAN","VEGETARIAN","WHEAT"],"dish_type":"Aktionsessen 4"},{"name":"Fried Chicken Wings mit Barbecuesauce","prices":{"students":{"base_price":1.0,"price_per_unit":0.8,"unit":"100g"},"staff":{"base_price":1.0,"price_per_unit":1.0,"unit":"100g"},"guests":{"base_price":1.0,"price_per_unit":1.35,"unit":"100g"}},"labels":["CELERY","GARLIC","MEAT","MUSTARD","PHENYLALANINE","SWEETENERS"],"dish_type":"Aktionsessen 5"}]},{"date":"2022-08-05","dishes":[{"name":"Dinkelpfannkuchen mit Haselnuss-Nougat-Füllung und Vanillesauce","prices":{"students":{"base_price":0,"price_per_unit":0.8,"unit":"100g"},"staff":{"base_price":0,"price_per_unit":1.0,"unit":"100g"},"guests":{"base_price":0,"price_per_unit":1.35,"unit":"100g"}},"labels":["CEREAL","CHICKEN_EGGS","GLUTEN","HAZELNUTS","LACTOSE","MILK","SHELLFISH","SHELL_FRUITS","SOY","SPELT","VEGETARIAN"],"dish_type":"Aktionsessen 5"},{"name":"Gegrilltes Zanderfilet mit Zitrone","prices":{"students":{"base_price":1.5,"price_per_unit":0.8,"unit":"100g"},"staff":{"base_price":1.5,"price_per_unit":1.0,"unit":"100g"},"guests":{"base_price":1.5,"price_per_unit":1.35,"unit":"100g"}},"labels":["CEREAL","FISH","GLUTEN","LACTOSE","MILK","WHEAT"],"dish_type":"Aktionsessen 9"}]}],"version":"2.1"}