{"number":8,"year":2022,"days":[{"date":"2022-02-24","dishes":[{"name":"Curry sausage with honey ginger ketchup","prices":{"students":{"base_price":0.5,"price_per_unit":0.75,"unit":"100g"},"staff":{"base_price":0.5,"price_per_unit":0.9,"unit":"100g"},"guests":{"base_price":0.5,"price_per_unit":1.05,"unit":"100g"}},"labels":["BEEF","MEAT","MUSTARD","PHOSPATES","PORK"],"dish_type":"Self-Service"},{"name":"Fresh cream mushrooms","prices":{"students":{"base_price":0,"price_per_unit":0.75,"unit":"100g"},"staff":{"base_price":0,"price_per_unit":0.9,"unit":"100g"},"guests":{"base_price":0,"price_per_unit":1.05,"unit":"100g"}},"labels":["CEREAL","GARLIC","GLUTEN","LACTOSE","MILK","VEGETARIAN","WHEAT"],"dish_type":"Self-Service"},{"name":"Bread dumplings","prices":{"students":{"base_price":0,"price_per_unit":0.75,"unit":"100g"},"staff":{"base_price":0,"price_per_unit":0.9,"unit":"100g"},"guests":{"base_price":0,"price_per_unit":1.05,"unit":"100g"}},"labels":["CEREAL","CHICKEN_EGGS","DYESTUFF","GLUTEN","LACTOSE","MILK","VEGETARIAN","WHEAT"],"dish_type":"Self-Service"},{"name":"Zucchinis with carrots,salsify and green beans","prices":{"students":{"base_price":0,"price_per_unit":0.75,"unit":"100g"},"staff":{"base_price":0,"price_per_unit":0.9,"unit":"100g"},"guests":{"base_price":0,"price_per_unit":1.05,"unit":"100g"}},"labels":["GARLIC","VEGAN","VEGETARIAN"],"dish_type":"Self-Service"},{"name":"Vegetables of the day","prices":{"students":{"base_price":1.0,"price_per_unit":0.75,"unit":"100g"},"staff":{"base_price":1.0,"price_per_unit":0.9,"unit":"100g"},"guests":{"base_price":1.0,"price_per_unit":1.05,"unit":"100g"}},"labels":["MEAT"],"dish_type":"Self-Service"},{"name":"Soup of the day","prices":{"students":{"base_price":1.0,"price_per_unit":0.75,"unit":"100g"},"staff":{"base_price":1.0,"price_per_unit":0.9,"unit":"100g"},"guests":{"base_price":1.0,"price_per_unit":1.05,"unit":"100g"}},"labels":["MEAT"],"dish_type":"Self-Service"}]},{"date":"2022-02-25","dishes":[{"name":"Swedish köttbullar with lingonberry cream sauce","prices":{"students":{"base_price":1.0,"price_per_unit":0.75,"unit":"100g"},"staff":{"base_price":1.0,"price_per_unit":0.9,"unit":"100g"},"guests":{"base_price":1.0,"price_per_unit":1.05,"unit":"100g"}},"labels":["BEEF","CEREAL","CHICKEN_EGGS","GARLIC","GLUTEN","LACTOSE","MEAT","MILK","PORK","WHEAT"],"dish_type":"Self-Service"},{"name":"Kaiserschmarrn with apple sauce","prices":{"students":{"base_price":0,"price_per_unit":0.75,"unit":"100g"},"staff":{"base_price":0,"price_per_unit":0.9,"unit":"100g"},"guests":{"base_price":0,"price_per_unit":1.05,"unit":"100g"}},"labels":["ANTIOXIDANTS","CEREAL","CHICKEN_EGGS","GLUTEN","LACTOSE","MILK","VEGETARIAN","WHEAT"],"dish_type":"Self-Service"},{"name":"Parsley potatoes","prices":{"students":{"base_price":0,"price_per_unit":0.75,"unit":"100g"},"staff":{"base_price":0,"price_per_unit":0.9,"unit":"100g"},"guests":{"base_price":0,"price_per_unit":1.05,"unit":"100g"}},"labels":["LACTOSE","MILK","VEGAN","VEGETARIAN"],"dish_type":"Self-Service"},{"name":"Peas, natural","prices":{"students":{"base_price":0,"price_per_unit":0.75,"unit":"100g"},"staff":{"base_price":0,"price_per_unit":0.9,"unit":"100g"},"guests":{"base_price":0,"price_per_unit":1.05,"unit":"100g"}},"labels":["VEGAN","VEGETARIAN"],"dish_type":"Self-Service"},{"name":"Vegetables of the day","prices":{"students":{"base_price":1.0,"price_per_unit":0.75,"unit":"100g"},"staff":{"base_price":1.0,"price_per_unit":0.9,"unit":"100g"},"guests":{"base_price":1.0,"price_per_unit":1.05,"unit":"100g"}},"labels":["MEAT"],"dish_type":"Self-Service"},{"name":"Soup of the day","prices":{"students":{"base_price":1.0,"price_per_unit":0.75,"unit":"100g"},"staff":{"base_price":1.0,"price_per_unit":0.9,"unit":"100g"},"guests":{"base_price":1.0,"price_per_unit":1.05,"unit":"100g"}},"labels":["MEAT"],"dish_type":"Self-Service"},{"name":"Action dessert","prices":{"students":{"base_price":1.0,"price_per_unit":0.75,"unit":"100g"},"staff":{"base_price":1.0,"price_per_unit":0.9,"unit":"100g"},"guests":{"base_price":1.0,"price_per_unit":1.05,"unit":"100g"}},"labels":["MEAT"],"dish_type":"Dessert"}]}],"version":"2.1"}