{"number":2,"year":2026,"days":[{"date":"2026-01-09","dishes":[{"name":"Ravioli mit Tomate-Basilikumfüllung , dazu Tomatensahnesauce","prices":{"students":{"base_price":0,"price_per_unit":0.9,"unit":"100g"},"staff":{"base_price":0,"price_per_unit":1.15,"unit":"100g"},"guests":{"base_price":0,"price_per_unit":1.6,"unit":"100g"}},"labels":["CEREAL","CHICKEN_EGGS","GLUTEN","LACTOSE","MILK","VEGETARIAN","WHEAT"],"dish_type":"Pasta"},{"name":"Pasta mit Champignonrahmsauce","prices":{"students":{"base_price":0,"price_per_unit":0.9,"unit":"100g"},"staff":{"base_price":0,"price_per_unit":1.15,"unit":"100g"},"guests":{"base_price":0,"price_per_unit":1.6,"unit":"100g"}},"labels":["VEGETARIAN"],"dish_type":"Pasta"},{"name":"Wurstgulasch","prices":{"students":{"base_price":0.5,"price_per_unit":0.9,"unit":"100g"},"staff":{"base_price":0.5,"price_per_unit":1.15,"unit":"100g"},"guests":{"base_price":0.5,"price_per_unit":1.6,"unit":"100g"}},"labels":["ANTIOXIDANTS","BEEF","CEREAL","GARLIC","GLUTEN","MEAT","PHOSPHATES","PORK","WHEAT"],"dish_type":"Grill"},{"name":"Fischcurry orientalische Art mit Broccoli, Zwiebeln","prices":{"students":{"base_price":1.5,"price_per_unit":0.9,"unit":"100g"},"staff":{"base_price":1.5,"price_per_unit":1.15,"unit":"100g"},"guests":{"base_price":1.5,"price_per_unit":1.6,"unit":"100g"}},"labels":["CEREAL","FISH","GLUTEN","MUSTARD","WHEAT"],"dish_type":"Fisch"},{"name":"Apfelkücherl mit Vanillesauce","prices":{"students":{"base_price":1.0,"price_per_unit":0.9,"unit":"100g"},"staff":{"base_price":1.0,"price_per_unit":1.15,"unit":"100g"},"guests":{"base_price":1.0,"price_per_unit":1.6,"unit":"100g"}},"labels":["CEREAL","CHICKEN_EGGS","GLUTEN","LACTOSE","MEAT","MILK","WHEAT"],"dish_type":"Süßspeise"},{"name":"Mexikanisches Chili sin carne mit Süßkartoffeln","prices":{"students":{"base_price":0,"price_per_unit":0.9,"unit":"100g"},"staff":{"base_price":0,"price_per_unit":1.15,"unit":"100g"},"guests":{"base_price":0,"price_per_unit":1.6,"unit":"100g"}},"labels":["VEGAN","VEGETARIAN"],"dish_type":"Vegan"}]}],"version":"2.1"}