{"number":19,"year":2024,"days":[{"date":"2024-05-06","dishes":[{"name":"Tortellini mit Ricotta-Spinat-Füllung in Kräutersauce","prices":{"students":{"base_price":0,"price_per_unit":0.8,"unit":"100g"},"staff":{"base_price":0,"price_per_unit":1.0,"unit":"100g"},"guests":{"base_price":0,"price_per_unit":1.35,"unit":"100g"}},"labels":["CEREAL","CHICKEN_EGGS","GARLIC","GLUTEN","LACTOSE","MILK","VEGETARIAN","WHEAT"],"dish_type":"Pasta"},{"name":"Fränkische Bratwurst (1 Stück)","prices":{"students":{"base_price":0.5,"price_per_unit":0.8,"unit":"100g"},"staff":{"base_price":0.5,"price_per_unit":1.0,"unit":"100g"},"guests":{"base_price":0.5,"price_per_unit":1.35,"unit":"100g"}},"labels":["ANTIOXIDANTS","BEEF","MEAT","PHOSPATES","PORK"],"dish_type":"Grill"},{"name":"Buntes Gemüse in scharfer Kokosmilch","prices":{"students":{"base_price":0,"price_per_unit":0.8,"unit":"100g"},"staff":{"base_price":0,"price_per_unit":1.0,"unit":"100g"},"guests":{"base_price":0,"price_per_unit":1.35,"unit":"100g"}},"labels":["ANTIOXIDANTS","GARLIC","MUSTARD","PRESERVATIVES","VEGAN","VEGETARIAN"],"dish_type":"Wok"},{"name":"Tagessuppe","prices":{"students":{"base_price":0,"price_per_unit":0.33,"unit":"100g"},"staff":{"base_price":0,"price_per_unit":0.65,"unit":"100g"},"guests":{"base_price":0,"price_per_unit":1.35,"unit":"100g"}},"labels":["MEAT"],"dish_type":"Studitopf"},{"name":"Basmatireis","prices":{"students":{"base_price":0,"price_per_unit":0.8,"unit":"100g"},"staff":{"base_price":0,"price_per_unit":1.0,"unit":"100g"},"guests":{"base_price":0,"price_per_unit":1.35,"unit":"100g"}},"labels":["VEGAN","VEGETARIAN"],"dish_type":"Beilagen"},{"name":"Röstkartoffeln","prices":{"students":{"base_price":0,"price_per_unit":0.8,"unit":"100g"},"staff":{"base_price":0,"price_per_unit":1.0,"unit":"100g"},"guests":{"base_price":0,"price_per_unit":1.35,"unit":"100g"}},"labels":["VEGAN","VEGETARIAN"],"dish_type":"Beilagen"},{"name":"Sauerkraut","prices":{"students":{"base_price":0,"price_per_unit":0.8,"unit":"100g"},"staff":{"base_price":0,"price_per_unit":1.0,"unit":"100g"},"guests":{"base_price":0,"price_per_unit":1.35,"unit":"100g"}},"labels":["VEGAN","VEGETARIAN"],"dish_type":"Beilagen"},{"name":"Frischer Brokkoli","prices":{"students":{"base_price":0,"price_per_unit":0.8,"unit":"100g"},"staff":{"base_price":0,"price_per_unit":1.0,"unit":"100g"},"guests":{"base_price":0,"price_per_unit":1.35,"unit":"100g"}},"labels":["VEGAN","VEGETARIAN"],"dish_type":"Beilagen"},{"name":"Täglich frische Salatbar","prices":{"students":{"base_price":0,"price_per_unit":0.8,"unit":"100g"},"staff":{"base_price":0,"price_per_unit":1.0,"unit":"100g"},"guests":{"base_price":0,"price_per_unit":1.35,"unit":"100g"}},"labels":["ANTIOXIDANTS","DYESTUFF","GARLIC","LACTOSE","MEAT","MILK","MUSTARD","SWEETENERS"],"dish_type":"Beilagen"},{"name":"Sahnequark mit Vanille","prices":{"students":{"base_price":0,"price_per_unit":0.8,"unit":"100g"},"staff":{"base_price":0,"price_per_unit":1.0,"unit":"100g"},"guests":{"base_price":0,"price_per_unit":1.35,"unit":"100g"}},"labels":["LACTOSE","MILK","SOY","VEGETARIAN"],"dish_type":"Beilagen"}]},{"date":"2024-05-07","dishes":[{"name":"Dinkelnudelpfanne Griechischer Art mit Oliven,Schafskäse und Knoblauch","prices":{"students":{"base_price":0,"price_per_unit":0.8,"unit":"100g"},"staff":{"base_price":0,"price_per_unit":1.0,"unit":"100g"},"guests":{"base_price":0,"price_per_unit":1.35,"unit":"100g"}},"labels":["ANTIOXIDANTS","CEREAL","DYESTUFF","GARLIC","GLUTEN","LACTOSE","MILK","SPELT","VEGETARIAN"],"dish_type":"Pasta"},{"name":"Tagessuppe","prices":{"students":{"base_price":0,"price_per_unit":0.33,"unit":"100g"},"staff":{"base_price":0,"price_per_unit":0.65,"unit":"100g"},"guests":{"base_price":0,"price_per_unit":1.35,"unit":"100g"}},"labels":["MEAT"],"dish_type":"Studitopf"},{"name":"Münchner Biergulasch vom Rind","prices":{"students":{"base_price":1.0,"price_per_unit":0.8,"unit":"100g"},"staff":{"base_price":1.0,"price_per_unit":1.0,"unit":"100g"},"guests":{"base_price":1.0,"price_per_unit":1.35,"unit":"100g"}},"labels":["ALCOHOL","BARLEY","BEEF","CEREAL","GARLIC","GLUTEN","MEAT","WHEAT"],"dish_type":"Fleisch"},{"name":"Frischer Schrobenhausener Spargel (g.g.A.)","prices":{"students":{"base_price":0,"price_per_unit":0.8,"unit":"100g"},"staff":{"base_price":0,"price_per_unit":1.0,"unit":"100g"},"guests":{"base_price":0,"price_per_unit":1.35,"unit":"100g"}},"labels":["VEGAN","VEGETARIAN"],"dish_type":"Vegan"},{"name":"Vegane Spargelsauce","prices":{"students":{"base_price":0,"price_per_unit":0.8,"unit":"100g"},"staff":{"base_price":0,"price_per_unit":1.0,"unit":"100g"},"guests":{"base_price":0,"price_per_unit":1.35,"unit":"100g"}},"labels":["CEREAL","DYESTUFF","GLUTEN","MUSTARD","SULFITES","SULPHURS","VEGAN","VEGETARIAN","WHEAT"],"dish_type":"Vegan"},{"name":"Neue Kartoffeln","prices":{"students":{"base_price":0,"price_per_unit":0.8,"unit":"100g"},"staff":{"base_price":0,"price_per_unit":1.0,"unit":"100g"},"guests":{"base_price":0,"price_per_unit":1.35,"unit":"100g"}},"labels":["LACTOSE","MEAT","MILK"],"dish_type":"Beilagen"},{"name":"Semmelknödel","prices":{"students":{"base_price":0,"price_per_unit":0.8,"unit":"100g"},"staff":{"base_price":0,"price_per_unit":1.0,"unit":"100g"},"guests":{"base_price":0,"price_per_unit":1.35,"unit":"100g"}},"labels":["CEREAL","CHICKEN_EGGS","GLUTEN","LACTOSE","MILK","VEGETARIAN","WHEAT"],"dish_type":"Beilagen"},{"name":"Kerbel-Zitronen-Hollandaise","prices":{"students":{"base_price":0,"price_per_unit":0.8,"unit":"100g"},"staff":{"base_price":0,"price_per_unit":1.0,"unit":"100g"},"guests":{"base_price":0,"price_per_unit":1.35,"unit":"100g"}},"labels":["CHICKEN_EGGS","DYESTUFF","LACTOSE","MILK","MUSTARD","SULFITES","SULPHURS","VEGETARIAN"],"dish_type":"Beilagen"},{"name":"Kaisergemüse","prices":{"students":{"base_price":0,"price_per_unit":0.8,"unit":"100g"},"staff":{"base_price":0,"price_per_unit":1.0,"unit":"100g"},"guests":{"base_price":0,"price_per_unit":1.35,"unit":"100g"}},"labels":["VEGAN","VEGETARIAN"],"dish_type":"Beilagen"},{"name":"Täglich frische Salatbar","prices":{"students":{"base_price":0,"price_per_unit":0.8,"unit":"100g"},"staff":{"base_price":0,"price_per_unit":1.0,"unit":"100g"},"guests":{"base_price":0,"price_per_unit":1.35,"unit":"100g"}},"labels":["ANTIOXIDANTS","DYESTUFF","GARLIC","LACTOSE","MEAT","MILK","MUSTARD","SWEETENERS"],"dish_type":"Beilagen"},{"name":"Cremige Vanillepolenta mit frischen Erdbeeren","prices":{"students":{"base_price":0,"price_per_unit":0.8,"unit":"100g"},"staff":{"base_price":0,"price_per_unit":1.0,"unit":"100g"},"guests":{"base_price":0,"price_per_unit":1.35,"unit":"100g"}},"labels":["LACTOSE","MILK","VEGETARIAN"],"dish_type":"Beilagen"}]},{"date":"2024-05-08","dishes":[{"name":"Allgäuer Käsespätzle mit Röstzwiebeln","prices":{"students":{"base_price":0,"price_per_unit":0.8,"unit":"100g"},"staff":{"base_price":0,"price_per_unit":1.0,"unit":"100g"},"guests":{"base_price":0,"price_per_unit":1.35,"unit":"100g"}},"labels":["CEREAL","CHICKEN_EGGS","DYESTUFF","GLUTEN","LACTOSE","MILK","SPELT","VEGETARIAN","WHEAT"],"dish_type":"Pasta"},{"name":"Gegrilltes Putensteak (1 Stück) mit Kräuterbutter","prices":{"students":{"base_price":1.0,"price_per_unit":0.8,"unit":"100g"},"staff":{"base_price":1.0,"price_per_unit":1.0,"unit":"100g"},"guests":{"base_price":1.0,"price_per_unit":1.35,"unit":"100g"}},"labels":["CEREAL","GARLIC","GLUTEN","LACTOSE","MEAT","MILK","WHEAT"],"dish_type":"Grill"},{"name":"Tagessuppe","prices":{"students":{"base_price":0,"price_per_unit":0.33,"unit":"100g"},"staff":{"base_price":0,"price_per_unit":0.65,"unit":"100g"},"guests":{"base_price":0,"price_per_unit":1.35,"unit":"100g"}},"labels":["MEAT"],"dish_type":"Studitopf"},{"name":"Bunte Reis-Gemüse-Pfanne mit Chunks aus Erbsenprotein","prices":{"students":{"base_price":0,"price_per_unit":0.8,"unit":"100g"},"staff":{"base_price":0,"price_per_unit":1.0,"unit":"100g"},"guests":{"base_price":0,"price_per_unit":1.35,"unit":"100g"}},"labels":["CEREAL","GLUTEN","SOY","VEGAN","VEGETARIAN","WHEAT"],"dish_type":"Vegan"},{"name":"Kartoffelgratin","prices":{"students":{"base_price":0,"price_per_unit":0.8,"unit":"100g"},"staff":{"base_price":0,"price_per_unit":1.0,"unit":"100g"},"guests":{"base_price":0,"price_per_unit":1.35,"unit":"100g"}},"labels":["CHICKEN_EGGS","GARLIC","LACTOSE","MILK","VEGETARIAN"],"dish_type":"Beilagen"},{"name":"Gemüse Toscana","prices":{"students":{"base_price":0,"price_per_unit":0.8,"unit":"100g"},"staff":{"base_price":0,"price_per_unit":1.0,"unit":"100g"},"guests":{"base_price":0,"price_per_unit":1.35,"unit":"100g"}},"labels":["VEGAN","VEGETARIAN"],"dish_type":"Beilagen"},{"name":"Täglich frische Salatbar","prices":{"students":{"base_price":0,"price_per_unit":0.8,"unit":"100g"},"staff":{"base_price":0,"price_per_unit":1.0,"unit":"100g"},"guests":{"base_price":0,"price_per_unit":1.35,"unit":"100g"}},"labels":["ANTIOXIDANTS","DYESTUFF","GARLIC","LACTOSE","MEAT","MILK","MUSTARD","SWEETENERS"],"dish_type":"Beilagen"},{"name":"Frische Erdbeeren mit Sahne","prices":{"students":{"base_price":0,"price_per_unit":0.8,"unit":"100g"},"staff":{"base_price":0,"price_per_unit":1.0,"unit":"100g"},"guests":{"base_price":0,"price_per_unit":1.35,"unit":"100g"}},"labels":["LACTOSE","MILK","VEGETARIAN"],"dish_type":"Beilagen"}]},{"date":"2024-05-09","dishes":[{"name":"Christi Himmelfahrt","prices":{"students":{"base_price":0,"price_per_unit":0.8,"unit":"100g"},"staff":{"base_price":0,"price_per_unit":1.0,"unit":"100g"},"guests":{"base_price":0,"price_per_unit":1.35,"unit":"100g"}},"labels":["MEAT"],"dish_type":"Beilagen"}]},{"date":"2024-05-10","dishes":[{"name":"Geschlossen","prices":{"students":{"base_price":0,"price_per_unit":0.8,"unit":"100g"},"staff":{"base_price":0,"price_per_unit":1.0,"unit":"100g"},"guests":{"base_price":0,"price_per_unit":1.35,"unit":"100g"}},"labels":["MEAT"],"dish_type":"Beilagen"}]}],"version":"2.1"}