{"number":10,"year":2026,"days":[{"date":"2026-03-02","dishes":[{"name":"Schweinswürstel (3 Stück) mit Sauerkraut","prices":{"students":null,"staff":null,"guests":null},"labels":["ANTIOXIDANTS","MEAT","PHOSPHATES","PORK"],"dish_type":"Grill"},{"name":"Kokos-Mienudeln mit gebratenem Tofu und Thai-Gemüse","prices":{"students":null,"staff":null,"guests":null},"labels":["CEREAL","GLUTEN","MUSTARD","SOY","VEGAN","VEGETARIAN","WHEAT"],"dish_type":"Wok"},{"name":"Pikantes Kartoffelchili","prices":{"students":null,"staff":null,"guests":null},"labels":["VEGAN","VEGETARIAN"],"dish_type":"Studitopf"},{"name":"Tagessuppe","prices":{"students":null,"staff":null,"guests":null},"labels":["MEAT"],"dish_type":"Tagessupe, Brot, Obst"},{"name":"Kirsch-Mascarpone-Creme","prices":{"students":null,"staff":null,"guests":null},"labels":["ALMONDS","LACTOSE","MILK","SHELLFISH","SHELL_FRUITS","VEGETARIAN"],"dish_type":"Dessert (Glas)"}]}],"version":"2.1"}