{"version":"2.1","canteen_id":"mensa-bildungscampus-heilbronn","weeks":[{"number":3,"year":2026,"days":[{"date":"2026-01-13","dishes":[{"name":"Apfelküchlein mit Haferpudding","prices":{"students":{"base_price":0,"price_per_unit":0.9,"unit":"Portion"},"staff":{"base_price":0,"price_per_unit":1.4,"unit":"Portion"},"guests":{"base_price":0,"price_per_unit":2.0,"unit":"Portion"}},"labels":[],"dish_type":"Dessert"},{"name":"Hausgemachte Creme mit Crunch","prices":{"students":{"base_price":0,"price_per_unit":0.9,"unit":"Portion"},"staff":{"base_price":0,"price_per_unit":1.4,"unit":"Portion"},"guests":{"base_price":0,"price_per_unit":2.0,"unit":"Portion"}},"labels":[],"dish_type":"Dessert vegan"},{"name":"Kartoffelcremesuppe (vegan)","prices":{"students":{"base_price":0,"price_per_unit":0.9,"unit":"Portion"},"staff":{"base_price":0,"price_per_unit":1.4,"unit":"Portion"},"guests":{"base_price":0,"price_per_unit":2.0,"unit":"Portion"}},"labels":[],"dish_type":"Suppentopf"},{"name":"Welsfilet in Maispanade auf Tomaten-Oliven Sugo und Zitronen-Couscous","prices":{"students":{"base_price":0,"price_per_unit":0.99,"unit":"Portion"},"staff":{"base_price":0,"price_per_unit":1.35,"unit":"Portion"},"guests":{"base_price":0,"price_per_unit":2.0,"unit":"Portion"}},"labels":[],"dish_type":"Tierisch"},{"name":"Veganer Hot Dog mit Essiggurken, Coleslaw, Röstzwiebeln und Tortilla-Chips","prices":{"students":{"base_price":0,"price_per_unit":2.9,"unit":"Portion"},"staff":{"base_price":0,"price_per_unit":4.5,"unit":"Portion"},"guests":{"base_price":0,"price_per_unit":7.5,"unit":"Portion"}},"labels":[],"dish_type":"Vegan"},{"name":"Zucchini-Basilikum Pasta mit Mozzarella überbacken","prices":{"students":{"base_price":0,"price_per_unit":0.99,"unit":"Portion"},"staff":{"base_price":0,"price_per_unit":1.35,"unit":"Portion"},"guests":{"base_price":0,"price_per_unit":2.0,"unit":"Portion"}},"labels":[],"dish_type":"Vegetarisch"}]},{"date":"2026-01-14","dishes":[{"name":"Gelierte Kirschen mit Zimtsahne","prices":{"students":{"base_price":0,"price_per_unit":0.9,"unit":"Portion"},"staff":{"base_price":0,"price_per_unit":1.4,"unit":"Portion"},"guests":{"base_price":0,"price_per_unit":2.0,"unit":"Portion"}},"labels":[],"dish_type":"Dessert"},{"name":"Joghurtmousse mit Erdbeertopping","prices":{"students":{"base_price":0,"price_per_unit":0.9,"unit":"Portion"},"staff":{"base_price":0,"price_per_unit":1.4,"unit":"Portion"},"guests":{"base_price":0,"price_per_unit":2.0,"unit":"Portion"}},"labels":[],"dish_type":"Dessert vegan"},{"name":"Cremesüppchen vom Blumenkohl und Curry","prices":{"students":{"base_price":0,"price_per_unit":0.9,"unit":"Portion"},"staff":{"base_price":0,"price_per_unit":1.4,"unit":"Portion"},"guests":{"base_price":0,"price_per_unit":2.0,"unit":"Portion"}},"labels":[],"dish_type":"Suppentopf"},{"name":"Hackbraten vom Hohenloher Rind mit Lauch-Erbsen und Knöpfle","prices":{"students":{"base_price":0,"price_per_unit":0.99,"unit":"Portion"},"staff":{"base_price":0,"price_per_unit":1.35,"unit":"Portion"},"guests":{"base_price":0,"price_per_unit":2.0,"unit":"Portion"}},"labels":[],"dish_type":"Tierisch"},{"name":"Kartoffel-Gemüse-Küchlein mit Tomatenjus und Couscous","prices":{"students":{"base_price":0,"price_per_unit":2.9,"unit":"Portion"},"staff":{"base_price":0,"price_per_unit":4.5,"unit":"Portion"},"guests":{"base_price":0,"price_per_unit":7.5,"unit":"Portion"}},"labels":[],"dish_type":"Vegan"},{"name":"Ofenfrische Pizza mit Gemüse und Käse","prices":{"students":{"base_price":0,"price_per_unit":0.99,"unit":"Portion"},"staff":{"base_price":0,"price_per_unit":1.35,"unit":"Portion"},"guests":{"base_price":0,"price_per_unit":2.0,"unit":"Portion"}},"labels":[],"dish_type":"Vegetarisch"}]},{"date":"2026-01-15","dishes":[{"name":"Haferjoghurt mit Granola","prices":{"students":{"base_price":0,"price_per_unit":0.9,"unit":"Portion"},"staff":{"base_price":0,"price_per_unit":1.4,"unit":"Portion"},"guests":{"base_price":0,"price_per_unit":2.0,"unit":"Portion"}},"labels":[],"dish_type":"Dessert"},{"name":"Schichtdessert mit Frucht im Glas","prices":{"students":{"base_price":0,"price_per_unit":0.9,"unit":"Portion"},"staff":{"base_price":0,"price_per_unit":1.4,"unit":"Portion"},"guests":{"base_price":0,"price_per_unit":2.0,"unit":"Portion"}},"labels":[],"dish_type":"Dessert vegan"},{"name":"Arabische Linsensuppe","prices":{"students":{"base_price":0,"price_per_unit":0.9,"unit":"Portion"},"staff":{"base_price":0,"price_per_unit":1.4,"unit":"Portion"},"guests":{"base_price":0,"price_per_unit":2.0,"unit":"Portion"}},"labels":[],"dish_type":"Suppentopf"},{"name":"Gyros vom Hällischen Landschwein mit Tzatziki und Pommes frites","prices":{"students":{"base_price":0,"price_per_unit":0.99,"unit":"Portion"},"staff":{"base_price":0,"price_per_unit":1.35,"unit":"Portion"},"guests":{"base_price":0,"price_per_unit":2.0,"unit":"Portion"}},"labels":[],"dish_type":"Tierisch"},{"name":"Schwäbische Linsen mit veganen Spätzle und Räuchertofu","prices":{"students":{"base_price":0,"price_per_unit":2.9,"unit":"Portion"},"staff":{"base_price":0,"price_per_unit":4.5,"unit":"Portion"},"guests":{"base_price":0,"price_per_unit":7.5,"unit":"Portion"}},"labels":[],"dish_type":"Vegan"},{"name":"Pasta mit geschmortem Rübenallelei in Knoblauchrahm","prices":{"students":{"base_price":0,"price_per_unit":0.99,"unit":"Portion"},"staff":{"base_price":0,"price_per_unit":1.35,"unit":"Portion"},"guests":{"base_price":0,"price_per_unit":2.0,"unit":"Portion"}},"labels":[],"dish_type":"Vegetarisch"}]},{"date":"2026-01-16","dishes":[{"name":"Chiapudding mit Mandelmilch und frischem Obst","prices":{"students":{"base_price":0,"price_per_unit":0.9,"unit":"Portion"},"staff":{"base_price":0,"price_per_unit":1.4,"unit":"Portion"},"guests":{"base_price":0,"price_per_unit":2.0,"unit":"Portion"}},"labels":[],"dish_type":"Dessert"},{"name":"Maisgrießbrei mit Apfelmus","prices":{"students":{"base_price":0,"price_per_unit":0.9,"unit":"Portion"},"staff":{"base_price":0,"price_per_unit":1.4,"unit":"Portion"},"guests":{"base_price":0,"price_per_unit":2.0,"unit":"Portion"}},"labels":[],"dish_type":"Dessert vegan"},{"name":"Asiatische Ramen Suppe","prices":{"students":{"base_price":0,"price_per_unit":0.9,"unit":"Portion"},"staff":{"base_price":0,"price_per_unit":1.4,"unit":"Portion"},"guests":{"base_price":0,"price_per_unit":2.0,"unit":"Portion"}},"labels":[],"dish_type":"Suppentopf"},{"name":"Gebackener Seehecht auf mediterranem Gemüse und hausgemachter Pasta","prices":{"students":{"base_price":0,"price_per_unit":0.99,"unit":"Portion"},"staff":{"base_price":0,"price_per_unit":1.35,"unit":"Portion"},"guests":{"base_price":0,"price_per_unit":2.0,"unit":"Portion"}},"labels":[],"dish_type":"Tierisch"},{"name":"Hausgemachte Pasta in Erdnußbutter Soße und Zitrone","prices":{"students":{"base_price":0,"price_per_unit":0.99,"unit":"Portion"},"staff":{"base_price":0,"price_per_unit":1.35,"unit":"Portion"},"guests":{"base_price":0,"price_per_unit":2.0,"unit":"Portion"}},"labels":[],"dish_type":"Vegan"},{"name":"Hausgemachte Gemüse-Quiche, dazu Blattsalat und Kräuterdip","prices":{"students":{"base_price":0,"price_per_unit":2.9,"unit":"Portion"},"staff":{"base_price":0,"price_per_unit":4.5,"unit":"Portion"},"guests":{"base_price":0,"price_per_unit":7.5,"unit":"Portion"}},"labels":[],"dish_type":"Vegetarisch"}]}]},{"number":4,"year":2026,"days":[{"date":"2026-01-19","dishes":[{"name":"Pochierte Birne mit Kürbiskrokant  und Schlagcreme","prices":{"students":{"base_price":0,"price_per_unit":0.9,"unit":"Portion"},"staff":{"base_price":0,"price_per_unit":1.4,"unit":"Portion"},"guests":{"base_price":0,"price_per_unit":2.0,"unit":"Portion"}},"labels":[],"dish_type":"Dessert"},{"name":"Zimt Quark mit Kekscrunch und Ahornsirup","prices":{"students":{"base_price":0,"price_per_unit":0.9,"unit":"Portion"},"staff":{"base_price":0,"price_per_unit":1.4,"unit":"Portion"},"guests":{"base_price":0,"price_per_unit":2.0,"unit":"Portion"}},"labels":[],"dish_type":"Dessert vegan"},{"name":"Gemüse-Kartoffel-Topf in Brühe","prices":{"students":{"base_price":0,"price_per_unit":0.9,"unit":"Portion"},"staff":{"base_price":0,"price_per_unit":1.4,"unit":"Portion"},"guests":{"base_price":0,"price_per_unit":2.0,"unit":"Portion"}},"labels":[],"dish_type":"Suppentopf"},{"name":"Hähnchenkeule aus dem Ofen mit Paprika-Sauce und Gemüsereis","prices":{"students":{"base_price":0,"price_per_unit":0.99,"unit":"Portion"},"staff":{"base_price":0,"price_per_unit":1.35,"unit":"Portion"},"guests":{"base_price":0,"price_per_unit":2.0,"unit":"Portion"}},"labels":[],"dish_type":"Tierisch"},{"name":"Erbsenrisotto mit gerösteten Sonnenblumenkernen  und Pfannengemüse","prices":{"students":{"base_price":0,"price_per_unit":2.9,"unit":"Portion"},"staff":{"base_price":0,"price_per_unit":4.5,"unit":"Portion"},"guests":{"base_price":0,"price_per_unit":7.5,"unit":"Portion"}},"labels":[],"dish_type":"Vegan"},{"name":"Gefüllter Pasta mit fruchtiger Tomatensauce","prices":{"students":{"base_price":0,"price_per_unit":0.99,"unit":"Portion"},"staff":{"base_price":0,"price_per_unit":1.35,"unit":"Portion"},"guests":{"base_price":0,"price_per_unit":2.0,"unit":"Portion"}},"labels":[],"dish_type":"Vegetarisch"}]},{"date":"2026-01-20","dishes":[{"name":"Kokos-Mandel-Pudding mit halbgefrorenen Himbeeren","prices":{"students":{"base_price":0,"price_per_unit":0.9,"unit":"Portion"},"staff":{"base_price":0,"price_per_unit":1.4,"unit":"Portion"},"guests":{"base_price":0,"price_per_unit":2.0,"unit":"Portion"}},"labels":[],"dish_type":"Dessert"},{"name":"Milchreis mit Schokoladensauce","prices":{"students":{"base_price":0,"price_per_unit":0.9,"unit":"Portion"},"staff":{"base_price":0,"price_per_unit":1.4,"unit":"Portion"},"guests":{"base_price":0,"price_per_unit":2.0,"unit":"Portion"}},"labels":[],"dish_type":"Dessert vegan"},{"name":"Brokkolicremesuppe mit Tomatenwürfeln\n","prices":{"students":{"base_price":0,"price_per_unit":0.9,"unit":"Portion"},"staff":{"base_price":0,"price_per_unit":1.4,"unit":"Portion"},"guests":{"base_price":0,"price_per_unit":2.0,"unit":"Portion"}},"labels":[],"dish_type":"Suppentopf"},{"name":"Gebratenes Hechtfilet mit gebackenem Blumenkohl und Dinkelreis","prices":{"students":{"base_price":0,"price_per_unit":0.99,"unit":"Portion"},"staff":{"base_price":0,"price_per_unit":1.35,"unit":"Portion"},"guests":{"base_price":0,"price_per_unit":2.0,"unit":"Portion"}},"labels":[],"dish_type":"Tierisch"},{"name":"Chili sin Carne mit Kräuterreis","prices":{"students":{"base_price":0,"price_per_unit":2.9,"unit":"Portion"},"staff":{"base_price":0,"price_per_unit":4.5,"unit":"Portion"},"guests":{"base_price":0,"price_per_unit":7.5,"unit":"Portion"}},"labels":[],"dish_type":"Vegan"},{"name":"Knöpflepfanne mit Porree und Gorgonzola","prices":{"students":{"base_price":0,"price_per_unit":0.99,"unit":"Portion"},"staff":{"base_price":0,"price_per_unit":1.35,"unit":"Portion"},"guests":{"base_price":0,"price_per_unit":2.0,"unit":"Portion"}},"labels":[],"dish_type":"Vegetarisch"}]},{"date":"2026-01-21","dishes":[{"name":"Hausgemachter Chia-Hafer-Pudding mit Fruchtmus","prices":{"students":{"base_price":0,"price_per_unit":0.9,"unit":"Portion"},"staff":{"base_price":0,"price_per_unit":1.4,"unit":"Portion"},"guests":{"base_price":0,"price_per_unit":2.0,"unit":"Portion"}},"labels":[],"dish_type":"Dessert"},{"name":"Gelierte Kirschen mit Puffreis Croutons","prices":{"students":{"base_price":0,"price_per_unit":0.9,"unit":"Portion"},"staff":{"base_price":0,"price_per_unit":1.4,"unit":"Portion"},"guests":{"base_price":0,"price_per_unit":2.0,"unit":"Portion"}},"labels":[],"dish_type":"Dessert vegan"},{"name":"Pikantes Süppchen mit jungem Lauch und Hafer","prices":{"students":{"base_price":0,"price_per_unit":0.9,"unit":"Portion"},"staff":{"base_price":0,"price_per_unit":1.4,"unit":"Portion"},"guests":{"base_price":0,"price_per_unit":2.0,"unit":"Portion"}},"labels":[],"dish_type":"Suppentopf"},{"name":"Hausgemachte Fleischküchle vom Hohenloher Rind mit Spätzle und Pilzrahmsauce","prices":{"students":{"base_price":0,"price_per_unit":0.99,"unit":"Portion"},"staff":{"base_price":0,"price_per_unit":1.35,"unit":"Portion"},"guests":{"base_price":0,"price_per_unit":2.0,"unit":"Portion"}},"labels":[],"dish_type":"Tierisch"},{"name":"Veganer Shepherd's pie mit Linsen, Wurzelgemüse und Sojahack","prices":{"students":{"base_price":0,"price_per_unit":0.99,"unit":"Portion"},"staff":{"base_price":0,"price_per_unit":1.35,"unit":"Portion"},"guests":{"base_price":0,"price_per_unit":2.0,"unit":"Portion"}},"labels":[],"dish_type":"Vegan"},{"name":"Pinke Pasta mit Knoblauchcreme und Brokkoli","prices":{"students":{"base_price":0,"price_per_unit":2.9,"unit":"Portion"},"staff":{"base_price":0,"price_per_unit":4.5,"unit":"Portion"},"guests":{"base_price":0,"price_per_unit":7.5,"unit":"Portion"}},"labels":[],"dish_type":"Vegetarisch"}]},{"date":"2026-01-22","dishes":[{"name":"Schokopudding mit frischer Frucht","prices":{"students":{"base_price":0,"price_per_unit":0.9,"unit":"Portion"},"staff":{"base_price":0,"price_per_unit":1.4,"unit":"Portion"},"guests":{"base_price":0,"price_per_unit":2.0,"unit":"Portion"}},"labels":[],"dish_type":"Dessert"},{"name":"Sahnejoghurtcreme mit Walnüssen und Fruchtsoße","prices":{"students":{"base_price":0,"price_per_unit":0.9,"unit":"Portion"},"staff":{"base_price":0,"price_per_unit":1.4,"unit":"Portion"},"guests":{"base_price":0,"price_per_unit":2.0,"unit":"Portion"}},"labels":[],"dish_type":"Dessert vegan"},{"name":"Champignonrahmsuppe mit Schnittlauch","prices":{"students":{"base_price":0,"price_per_unit":0.9,"unit":"Portion"},"staff":{"base_price":0,"price_per_unit":1.4,"unit":"Portion"},"guests":{"base_price":0,"price_per_unit":2.0,"unit":"Portion"}},"labels":[],"dish_type":"Suppentopf"},{"name":"Currywurst von der Oberländer mit Pommes frites","prices":{"students":{"base_price":0,"price_per_unit":0.99,"unit":"Portion"},"staff":{"base_price":0,"price_per_unit":1.35,"unit":"Portion"},"guests":{"base_price":0,"price_per_unit":2.0,"unit":"Portion"}},"labels":[],"dish_type":"Tierisch"},{"name":"Kichererbsen Tikka Masala mit Pasta","prices":{"students":{"base_price":0,"price_per_unit":0.99,"unit":"Portion"},"staff":{"base_price":0,"price_per_unit":1.35,"unit":"Portion"},"guests":{"base_price":0,"price_per_unit":2.0,"unit":"Portion"}},"labels":[],"dish_type":"Vegan"},{"name":"Cremige Polenta mit Ratatouille und Kräuter-Joghurtdip","prices":{"students":{"base_price":0,"price_per_unit":2.9,"unit":"Portion"},"staff":{"base_price":0,"price_per_unit":4.5,"unit":"Portion"},"guests":{"base_price":0,"price_per_unit":7.5,"unit":"Portion"}},"labels":[],"dish_type":"Vegetarisch"}]},{"date":"2026-01-23","dishes":[{"name":"Vanillepudding mit Fruchtkompott","prices":{"students":{"base_price":0,"price_per_unit":0.9,"unit":"Portion"},"staff":{"base_price":0,"price_per_unit":1.4,"unit":"Portion"},"guests":{"base_price":0,"price_per_unit":2.0,"unit":"Portion"}},"labels":[],"dish_type":"Dessert"},{"name":"Karamellcreme mit Crunch und Schoko\n","prices":{"students":{"base_price":0,"price_per_unit":0.9,"unit":"Portion"},"staff":{"base_price":0,"price_per_unit":1.4,"unit":"Portion"},"guests":{"base_price":0,"price_per_unit":2.0,"unit":"Portion"}},"labels":[],"dish_type":"Dessert vegan"},{"name":"Maiscremesuppe","prices":{"students":{"base_price":0,"price_per_unit":0.9,"unit":"Portion"},"staff":{"base_price":0,"price_per_unit":1.4,"unit":"Portion"},"guests":{"base_price":0,"price_per_unit":2.0,"unit":"Portion"}},"labels":[],"dish_type":"Suppentopf"},{"name":"Gebackenes Fischfilet mit Rosmarin-Drillingen und Remouladensoße","prices":{"students":{"base_price":0,"price_per_unit":0.99,"unit":"Portion"},"staff":{"base_price":0,"price_per_unit":1.35,"unit":"Portion"},"guests":{"base_price":0,"price_per_unit":2.0,"unit":"Portion"}},"labels":[],"dish_type":"Tierisch"},{"name":"Veganer Falafeldöner mit allem Drum und Dran","prices":{"students":{"base_price":0,"price_per_unit":2.9,"unit":"Portion"},"staff":{"base_price":0,"price_per_unit":4.5,"unit":"Portion"},"guests":{"base_price":0,"price_per_unit":7.5,"unit":"Portion"}},"labels":[],"dish_type":"Vegan"},{"name":"Geröstete Gemüsemaultaschen mit Zwiebelschmelze und Kartoffelsalat","prices":{"students":{"base_price":0,"price_per_unit":0.99,"unit":"Portion"},"staff":{"base_price":0,"price_per_unit":1.35,"unit":"Portion"},"guests":{"base_price":0,"price_per_unit":2.0,"unit":"Portion"}},"labels":[],"dish_type":"Vegetarisch"}]}]},{"number":5,"year":2026,"days":[{"date":"2026-01-26","dishes":[{"name":"Hausgemachtes Erdbeermousse","prices":{"students":{"base_price":0,"price_per_unit":0.9,"unit":"Portion"},"staff":{"base_price":0,"price_per_unit":1.4,"unit":"Portion"},"guests":{"base_price":0,"price_per_unit":2.0,"unit":"Portion"}},"labels":[],"dish_type":"Dessert"},{"name":"Apfelküchle mit Vanille-Pudding","prices":{"students":{"base_price":0,"price_per_unit":0.9,"unit":"Portion"},"staff":{"base_price":0,"price_per_unit":1.4,"unit":"Portion"},"guests":{"base_price":0,"price_per_unit":2.0,"unit":"Portion"}},"labels":[],"dish_type":"Dessert vegan"},{"name":"Tomatencremesüppchen mit Brotchips","prices":{"students":{"base_price":0,"price_per_unit":0.9,"unit":"Portion"},"staff":{"base_price":0,"price_per_unit":1.4,"unit":"Portion"},"guests":{"base_price":0,"price_per_unit":2.0,"unit":"Portion"}},"labels":[],"dish_type":"Suppentopf"},{"name":"Geröstete Maultaschen vom hällischen Landschwein mit Zwiebelschmelz und Kartoffelsalat","prices":{"students":{"base_price":0,"price_per_unit":0.99,"unit":"Portion"},"staff":{"base_price":0,"price_per_unit":1.35,"unit":"Portion"},"guests":{"base_price":0,"price_per_unit":2.0,"unit":"Portion"}},"labels":[],"dish_type":"Tierisch"},{"name":"Bunter Kartoffel-Gemüse-Gulasch, dazu Brötchen","prices":{"students":{"base_price":0,"price_per_unit":2.9,"unit":"Portion"},"staff":{"base_price":0,"price_per_unit":4.5,"unit":"Portion"},"guests":{"base_price":0,"price_per_unit":7.5,"unit":"Portion"}},"labels":[],"dish_type":"Vegan"},{"name":"Pasta in cremiger Lauch-Parmesansoße","prices":{"students":{"base_price":0,"price_per_unit":0.99,"unit":"Portion"},"staff":{"base_price":0,"price_per_unit":1.35,"unit":"Portion"},"guests":{"base_price":0,"price_per_unit":2.0,"unit":"Portion"}},"labels":[],"dish_type":"Vegetarisch"}]},{"date":"2026-01-27","dishes":[{"name":"Espressocreme mit Karamelltopping","prices":{"students":{"base_price":0,"price_per_unit":0.9,"unit":"Portion"},"staff":{"base_price":0,"price_per_unit":1.4,"unit":"Portion"},"guests":{"base_price":0,"price_per_unit":2.0,"unit":"Portion"}},"labels":[],"dish_type":"Dessert"},{"name":"Cremig gerührter Pudding mit Heidelbeeren","prices":{"students":{"base_price":0,"price_per_unit":0.9,"unit":"Portion"},"staff":{"base_price":0,"price_per_unit":1.4,"unit":"Portion"},"guests":{"base_price":0,"price_per_unit":2.0,"unit":"Portion"}},"labels":[],"dish_type":"Dessert vegan"},{"name":"Gemüsecremesuppe mit Kokos und Harissa","prices":{"students":{"base_price":0,"price_per_unit":0.9,"unit":"Portion"},"staff":{"base_price":0,"price_per_unit":1.4,"unit":"Portion"},"guests":{"base_price":0,"price_per_unit":2.0,"unit":"Portion"}},"labels":[],"dish_type":"Suppentopf"},{"name":"Schwäbische Linsen mit Geflügelsaiten und frischen Spätzle","prices":{"students":{"base_price":0,"price_per_unit":0.99,"unit":"Portion"},"staff":{"base_price":0,"price_per_unit":1.35,"unit":"Portion"},"guests":{"base_price":0,"price_per_unit":2.0,"unit":"Portion"}},"labels":[],"dish_type":"Tierisch"},{"name":"Hausgemachte Pasta mit veganer Bolognese","prices":{"students":{"base_price":0,"price_per_unit":2.9,"unit":"Portion"},"staff":{"base_price":0,"price_per_unit":4.5,"unit":"Portion"},"guests":{"base_price":0,"price_per_unit":7.5,"unit":"Portion"}},"labels":[],"dish_type":"Vegan"},{"name":"Gnocchi in Gorgonzolarahm und Spinat","prices":{"students":{"base_price":0,"price_per_unit":0.99,"unit":"Portion"},"staff":{"base_price":0,"price_per_unit":1.35,"unit":"Portion"},"guests":{"base_price":0,"price_per_unit":2.0,"unit":"Portion"}},"labels":[],"dish_type":"Vegetarisch"}]},{"date":"2026-01-28","dishes":[{"name":"Haferjoghurt mit Brombeeren und Minzsahne ","prices":{"students":{"base_price":0,"price_per_unit":0.9,"unit":"Portion"},"staff":{"base_price":0,"price_per_unit":1.4,"unit":"Portion"},"guests":{"base_price":0,"price_per_unit":2.0,"unit":"Portion"}},"labels":[],"dish_type":"Dessert"},{"name":"Kokospudding mit Bananenkuchen","prices":{"students":{"base_price":0,"price_per_unit":0.9,"unit":"Portion"},"staff":{"base_price":0,"price_per_unit":1.4,"unit":"Portion"},"guests":{"base_price":0,"price_per_unit":2.0,"unit":"Portion"}},"labels":[],"dish_type":"Dessert vegan"},{"name":"Hausgemachte Kürbissuppe","prices":{"students":{"base_price":0,"price_per_unit":0.9,"unit":"Portion"},"staff":{"base_price":0,"price_per_unit":1.4,"unit":"Portion"},"guests":{"base_price":0,"price_per_unit":2.0,"unit":"Portion"}},"labels":[],"dish_type":"Suppentopf"},{"name":"Rinderschmorbraten mit Grillgemüse und Ofenkartoffel","prices":{"students":{"base_price":0,"price_per_unit":0.99,"unit":"Portion"},"staff":{"base_price":0,"price_per_unit":1.35,"unit":"Portion"},"guests":{"base_price":0,"price_per_unit":2.0,"unit":"Portion"}},"labels":[],"dish_type":"Tierisch"},{"name":"Auberginen Curry mit gelben Möhren und Bohnen","prices":{"students":{"base_price":0,"price_per_unit":0.99,"unit":"Portion"},"staff":{"base_price":0,"price_per_unit":1.35,"unit":"Portion"},"guests":{"base_price":0,"price_per_unit":2.0,"unit":"Portion"}},"labels":[],"dish_type":"Vegan"},{"name":"Gemüse Enchiladas mit würzigem Käsetopping","prices":{"students":{"base_price":0,"price_per_unit":2.9,"unit":"Portion"},"staff":{"base_price":0,"price_per_unit":4.5,"unit":"Portion"},"guests":{"base_price":0,"price_per_unit":7.5,"unit":"Portion"}},"labels":[],"dish_type":"Vegetarisch"}]},{"date":"2026-01-29","dishes":[{"name":"Mandelpudding mit Rosinen","prices":{"students":{"base_price":0,"price_per_unit":0.9,"unit":"Portion"},"staff":{"base_price":0,"price_per_unit":1.4,"unit":"Portion"},"guests":{"base_price":0,"price_per_unit":2.0,"unit":"Portion"}},"labels":[],"dish_type":"Dessert"},{"name":"Vanillemousse mit Haferkeks und Schoko","prices":{"students":{"base_price":0,"price_per_unit":0.9,"unit":"Portion"},"staff":{"base_price":0,"price_per_unit":1.4,"unit":"Portion"},"guests":{"base_price":0,"price_per_unit":2.0,"unit":"Portion"}},"labels":[],"dish_type":"Dessert vegan"},{"name":"Kartoffel-Erbsen-Suppe mit Kräuterpesto","prices":{"students":{"base_price":0,"price_per_unit":0.9,"unit":"Portion"},"staff":{"base_price":0,"price_per_unit":1.4,"unit":"Portion"},"guests":{"base_price":0,"price_per_unit":2.0,"unit":"Portion"}},"labels":[],"dish_type":"Suppentopf"},{"name":"Lasagne al forno vom heimischen Rind","prices":{"students":{"base_price":0,"price_per_unit":0.99,"unit":"Portion"},"staff":{"base_price":0,"price_per_unit":1.35,"unit":"Portion"},"guests":{"base_price":0,"price_per_unit":2.0,"unit":"Portion"}},"labels":[],"dish_type":"Tierisch"},{"name":"Asia-Wok mit frischem Gemüse und Mie-Nudeln","prices":{"students":{"base_price":0,"price_per_unit":0.99,"unit":"Portion"},"staff":{"base_price":0,"price_per_unit":1.35,"unit":"Portion"},"guests":{"base_price":0,"price_per_unit":2.0,"unit":"Portion"}},"labels":[],"dish_type":"Vegan"},{"name":"Grünkern-Bratling mit Paprikareis und Tzatziki","prices":{"students":{"base_price":0,"price_per_unit":2.9,"unit":"Portion"},"staff":{"base_price":0,"price_per_unit":4.5,"unit":"Portion"},"guests":{"base_price":0,"price_per_unit":7.5,"unit":"Portion"}},"labels":[],"dish_type":"Vegetarisch"}]},{"date":"2026-01-30","dishes":[{"name":"Zwetschgenröster mit hausgemachten Steuseln","prices":{"students":{"base_price":0,"price_per_unit":0.9,"unit":"Portion"},"staff":{"base_price":0,"price_per_unit":1.4,"unit":"Portion"},"guests":{"base_price":0,"price_per_unit":2.0,"unit":"Portion"}},"labels":[],"dish_type":"Dessert"},{"name":"Mangopudding mit frischer Minze","prices":{"students":{"base_price":0,"price_per_unit":0.9,"unit":"Portion"},"staff":{"base_price":0,"price_per_unit":1.4,"unit":"Portion"},"guests":{"base_price":0,"price_per_unit":2.0,"unit":"Portion"}},"labels":[],"dish_type":"Dessert vegan"},{"name":"Selleriesuppe mit Ajvar und Kräutern","prices":{"students":{"base_price":0,"price_per_unit":0.9,"unit":"Portion"},"staff":{"base_price":0,"price_per_unit":1.4,"unit":"Portion"},"guests":{"base_price":0,"price_per_unit":2.0,"unit":"Portion"}},"labels":[],"dish_type":"Suppentopf"},{"name":"Seelachsfilet im Backteig mit Bratkartoffeln und Remouladensoße","prices":{"students":{"base_price":0,"price_per_unit":0.99,"unit":"Portion"},"staff":{"base_price":0,"price_per_unit":1.35,"unit":"Portion"},"guests":{"base_price":0,"price_per_unit":2.0,"unit":"Portion"}},"labels":[],"dish_type":"Tierisch"},{"name":"Schupfnudelpfanne mit Chinakohl \"Asia Style\" und Sweet-Chili-Dip","prices":{"students":{"base_price":0,"price_per_unit":2.9,"unit":"Portion"},"staff":{"base_price":0,"price_per_unit":4.5,"unit":"Portion"},"guests":{"base_price":0,"price_per_unit":7.5,"unit":"Portion"}},"labels":[],"dish_type":"Vegan"},{"name":"Hausgemachte Pasta mit Kräuterpesto und weißen Bohnen","prices":{"students":{"base_price":0,"price_per_unit":0.99,"unit":"Portion"},"staff":{"base_price":0,"price_per_unit":1.35,"unit":"Portion"},"guests":{"base_price":0,"price_per_unit":2.0,"unit":"Portion"}},"labels":[],"dish_type":"Vegetarisch"}]}]}]}