{"number":25,"year":2023,"days":[{"date":"2023-06-23","dishes":[{"name":"Kartoffel-Lauch-Suppe","prices":{"students":{"base_price":0.8,"price_per_unit":null,"unit":null},"staff":{"base_price":1.0,"price_per_unit":null,"unit":null},"guests":{"base_price":1.5,"price_per_unit":null,"unit":null}},"labels":["ANTIOXIDANTS","CELERY","SULPHURS","VEGETARIAN"],"dish_type":"Suppe"},{"name":"Veganes Blumenkohlcurry mit Kokosmilch","prices":{"students":{"base_price":2.0,"price_per_unit":null,"unit":null},"staff":{"base_price":2.8,"price_per_unit":null,"unit":null},"guests":{"base_price":3.6,"price_per_unit":null,"unit":null}},"labels":["ANTIOXIDANTS","CEREAL","OAT","VEGAN","VEGETARIAN"],"dish_type":"HG1"},{"name":"Fisch und Chips","prices":{"students":{"base_price":4.2,"price_per_unit":null,"unit":null},"staff":{"base_price":5.2,"price_per_unit":null,"unit":null},"guests":{"base_price":5.7,"price_per_unit":null,"unit":null}},"labels":["ANTIOXIDANTS","CEREAL","CHICKEN_EGGS","FISH","FISH","MILK","MUSTARD","SWEETENERS","WHEAT"],"dish_type":"HG2"},{"name":"Gemüsecocktail Sombrero","prices":{"students":{"base_price":1.2,"price_per_unit":null,"unit":null},"staff":{"base_price":1.4,"price_per_unit":null,"unit":null},"guests":{"base_price":1.9,"price_per_unit":null,"unit":null}},"labels":["ANTIOXIDANTS","CELERY","VEGAN","VEGETARIAN"],"dish_type":"B1"},{"name":"Gemischter Salat","prices":{"students":{"base_price":1.3,"price_per_unit":null,"unit":null},"staff":{"base_price":1.5,"price_per_unit":null,"unit":null},"guests":{"base_price":2.0,"price_per_unit":null,"unit":null}},"labels":["ANTIOXIDANTS","CELERY","SULFITES","SULPHURS","VEGETARIAN"],"dish_type":"B2"},{"name":"Country Kartoffeln","prices":{"students":{"base_price":1.4,"price_per_unit":null,"unit":null},"staff":{"base_price":1.5,"price_per_unit":null,"unit":null},"guests":{"base_price":2.0,"price_per_unit":null,"unit":null}},"labels":["CEREAL","VEGAN","VEGETARIAN","WHEAT"],"dish_type":"B3"},{"name":"Eierlikör Pudding","prices":{"students":{"base_price":1.0,"price_per_unit":null,"unit":null},"staff":{"base_price":1.2,"price_per_unit":null,"unit":null},"guests":{"base_price":1.6,"price_per_unit":null,"unit":null}},"labels":["ALCOHOL","CHICKEN_EGGS","MILK","VEGETARIAN"],"dish_type":"N1"},{"name":"Amaretto Creme","prices":{"students":{"base_price":1.2,"price_per_unit":null,"unit":null},"staff":{"base_price":1.5,"price_per_unit":null,"unit":null},"guests":{"base_price":1.7,"price_per_unit":null,"unit":null}},"labels":["ALMONDS","MILK","SHELL_FRUITS"],"dish_type":"N2"}]}],"version":"2.1"}