{"number":14,"year":2025,"days":[{"date":"2025-03-31","dishes":[{"name":"Mousse Erdbeer-Rhabarber-Geschmack","prices":{"students":{"base_price":1.0,"price_per_unit":0.8,"unit":"100g"},"staff":{"base_price":1.0,"price_per_unit":1.0,"unit":"100g"},"guests":{"base_price":1.0,"price_per_unit":1.35,"unit":"100g"}},"labels":["GELATIN","LACTOSE","MEAT","MILK"],"dish_type":"Dessert (Glas)"},{"name":"Schweineschnitzel Wiener Art (1 St체ck)","prices":{"students":{"base_price":1.0,"price_per_unit":0.8,"unit":"100g"},"staff":{"base_price":1.0,"price_per_unit":1.0,"unit":"100g"},"guests":{"base_price":1.0,"price_per_unit":1.35,"unit":"100g"}},"labels":["CEREAL","DYESTUFF","GARLIC","GLUTEN","MEAT","PORK","PRESERVATIVES","WHEAT"],"dish_type":"Fleisch"},{"name":"Tagessuppe","prices":{"students":{"base_price":1.0,"price_per_unit":0.8,"unit":"100g"},"staff":{"base_price":1.0,"price_per_unit":1.0,"unit":"100g"},"guests":{"base_price":1.0,"price_per_unit":1.35,"unit":"100g"}},"labels":["MEAT"],"dish_type":"Tagessupe, Brot, Obst"},{"name":"Teigtaschen gef체llt mit Steinpilzen und Frischk채se in Kr채utersauce","prices":{"students":{"base_price":0,"price_per_unit":0.8,"unit":"100g"},"staff":{"base_price":0,"price_per_unit":1.0,"unit":"100g"},"guests":{"base_price":0,"price_per_unit":1.35,"unit":"100g"}},"labels":["CEREAL","CHICKEN_EGGS","GARLIC","GLUTEN","LACTOSE","MILK","VEGETARIAN","WHEAT"],"dish_type":"Pasta"},{"name":"Teriyaki-Tofu","prices":{"students":{"base_price":0,"price_per_unit":0.8,"unit":"100g"},"staff":{"base_price":0,"price_per_unit":1.0,"unit":"100g"},"guests":{"base_price":0,"price_per_unit":1.35,"unit":"100g"}},"labels":["CEREAL","GARLIC","GLUTEN","MUSTARD","PRESERVATIVES","SESAME","SHELL_FRUITS","SOY","VEGAN","VEGETARIAN","WHEAT"],"dish_type":"Wok"}]}],"version":"2.1"}